currywrap/__init__.py
currywrap/partial.py
currywrap/search.py
currywrap-0.1.0.dist-info/METADATA
currywrap-0.1.0.dist-info/WHEEL
currywrap-0.1.0.dist-info/RECORD
