Metadata-Version: 2.1
Name: currywrap
Version: 0.1.0
Summary: 
Author: idorrington92
Author-email: idorrington92@gmail.com
Requires-Python: >=3.10,<4.0
Classifier: Programming Language :: Python :: 3
Classifier: Programming Language :: Python :: 3.10
Classifier: Programming Language :: Python :: 3.11
Requires-Dist: cachetools
Requires-Dist: numba
Requires-Dist: numpy
